chromedm/__init__.py
chromedm/driver.py
chromedm/errors.py
chromedm/logs.py
chromedm/manager.py
chromedm/settings.py
chromedm/utils.py
chromedm-0.1.10.0.dist-info/LICENSE
chromedm-0.1.10.0.dist-info/METADATA
chromedm-0.1.10.0.dist-info/WHEEL
chromedm-0.1.10.0.dist-info/top_level.txt
chromedm-0.1.10.0.dist-info/RECORD
