Metadata-Version: 2.1
Name: chromedm
Version: 0.1.10.0
Summary: A package that downloads and manage Chromedriver
Author: Jiefu Chen
Author-email: keppa1991@163.com
License: MIT
Keywords: chromedriver,chrome,selenium,chromedm
Classifier: Programming Language :: Python :: 3
Classifier: License :: OSI Approved :: MIT License
Classifier: Operating System :: Unix
Classifier: Operating System :: MacOS :: MacOS X
Classifier: Operating System :: Microsoft :: Windows
Requires-Python: >=3.10
License-File: LICENSE
Requires-Dist: aiohttp (>=3.8.4)
Requires-Dist: packaging (>=23.1)
Requires-Dist: pandas (>=2.0.3)
Requires-Dist: pyarrow (>=12.0.1)
